tradingpython/__init__.py
tradingpython-0.0.1.dist-info/WHEEL
tradingpython-0.0.1.dist-info/METADATA
tradingpython-0.0.1.dist-info/RECORD
