Metadata-Version: 2.1
Name: tradingpython
Version: 0.0.1
Summary: An amazing python package for backtesting trading strategies, real-time trading, and more.
Author-email: Azat <multi.scooper.0f@icloud.com>
Project-URL: Home, https://tradingpython.com 
